pal/__init__.py
pal/ai_util.py
pal/main.py
pal/plugins/browse.py
pal/plugins/create.py
pal/plugins/weather.py
sofapal-0.0.9.dist-info/LICENSE
sofapal-0.0.9.dist-info/METADATA
sofapal-0.0.9.dist-info/WHEEL
sofapal-0.0.9.dist-info/entry_points.txt
sofapal-0.0.9.dist-info/top_level.txt
sofapal-0.0.9.dist-info/RECORD
