Metadata-Version: 2.1
Name: sofapal
Version: 0.0.9
Summary: A modular command-line interface with AI function calling
Home-page: https://github.com/slumberdemon/pal
Author: SlumberDemon
Author-email: hi@sofa.sh
License: MIT
Project-URL: Bug Reports, https://github.com/slumberdemon/pal/issues
Project-URL: Source, https://github.com/slumberdemon/pal
Classifier: License :: OSI Approved :: MIT License
Classifier: Programming Language :: Python :: 3
Classifier: Programming Language :: Python :: 3.7
Classifier: Programming Language :: Python :: 3.8
Classifier: Programming Language :: Python :: 3.9
Classifier: Programming Language :: Python :: 3.10
Classifier: Programming Language :: Python :: 3.11
Classifier: Programming Language :: Python :: 3.12
License-File: LICENSE
Requires-Dist: inquirerpy
Requires-Dist: pytermgui
